rtl/packer.sv
module packer( 

    input aclk, 
    input aresetn, 

    input [7:0] r,g,b, 
    input eol, 
    output in_stream_ready, //backpressure signal going back to pixel_gen
    input valid, 
    input sof, //start of frame

    output [31:0]   out_stream_tdata, 
    output [3:0]    out_stream_tkeep, 
    output          out_stream_tlast, 
    input           out_stream_tready, 
    output          out_stream_tvalid, 
    output [0:0]    out_stream_tuser   
); 

reg [1:0] state_reg = 2'b0; 

wire [1:0] state = sof ? 2'b00 : state_reg; 
wire state0 = (state == 2'b0); 

reg sof_reg; 
reg [7:0]   last_r, last_g, last_b; 

//combinational 
reg[31:0]   tdata; 
reg         tvalid; 
reg         ready;

always @(posedge aclk) begin
    if(aresetn) begin
        //advance state if valid and... 
        if(valid) begin 
            //...if in state 0 or destination is ready
            if(state0 || out_stream_tready) begin 
                if (eol) begin //stay synchronised to start of new line - so reset to state 0 on eol
                    state_reg <= 2'b0;
                end 
                else begin 
                    state_reg <= state + 2'b1; 
                end 

                last_r <= r; 
                last_g <= g; 
                last_b <= b; 
            end 

            //store the sof flag when it is set (it can't be read in this cycle because the data isn't ready)
            if (sof) begin
                sof_reg <= 1'b1; 
            end
            //reset it after it has been read by the VDMA 
            else if (valid & out_stream_tready) begin
                sof_reg <= 1'b0;
            end 
        end 
    end
    else begin 
        state_reg <= 2'b0; 
        sof_reg <= 1'b0; 
    end 
end 

always @* begin 
    case ({state}) 
        2'b00: begin 
            //output is not complete (valid) in this state --> means we are always ready for the next pixel
            tdata = {g, last_r, last_b, last_g}; //don't care since valid is false - just copy another state
            tvalid = 1'b0; 
            ready = 1'b1;
        end 
        2'b01: begin 
            tdata = {g, last_r, last_b, last_g}; 
            tvalid = valid;
            ready = out_stream_tready; 
        end 
        2'b10: begin 
            tdata = {b, g, last_r, last_b}; 
            tvalid = valid; 
            ready = out_stream_tready; 
        end 
        2'b11: begin 
            tdata = {r,b,g, last_r}; 
            tvalid = valid; 
            ready = out_stream_tready; 
        end 
        default: begin 
            tdata = {g, last_r, last_b, last_g}; 
            tvalid = 1'b0; 
            ready = 1'b1; 
        end 
    endcase
end 

assign in_stream_ready = ready; 
assign out_stream_tlast = eol; //eol goes high on the last pixel of each row 
assign out_stream_tuser = sof_reg; //signal to vdma that there is a start of frame 
assign out_stream_tkeep = 4'hf; //all 4 bytes are valid - assume a line length is a multiple of 4 bytes
assign out_stream_tdata = tdata; 
assign out_stream_tvalid = tvalid; 

endmodule

rtl/pixel_generator.sv
module pixel_generator(
    input out_stream_aclk, 
    input s_axi_lite_aclk, 
    input axi_resetn, 
    input periph_resetn, 

    //stream output 
    output [31:0]   out_stream_tdata, 
    output [3:0]    out_stream_tkeep,
    output          out_stream_tlast,
    input           out_stream_tready, //ready signal coming from the VDMA 
    output          out_stream_tvalid, 
    output [0:0]    out_stream_tuser, 

    //AXI-Lite S
    input [AXI_LITE_ADDR_WIDTH-1:0] s_axi_lite_araddr,
    output          s_axi_lite_arready,
    input           s_axi_lite_arvalid,

    input [AXI_LITE_ADDR_WIDTH-1:0]     s_axi_lite_awaddr,
    output          s_axi_lite_awready,
    input           s_axi_lite_awvalid,

    input           s_axi_lite_bready,
    output [1:0]    s_axi_lite_bresp,
    output          s_axi_lite_bvalid,

    output [31:0]   s_axi_lite_rdata,
    input           s_axi_lite_rready,
    output [1:0]    s_axi_lite_rresp,
    output          s_axi_lite_rvalid,

    input  [31:0]   s_axi_lite_wdata,
    output          s_axi_lite_wready,
    input           s_axi_lite_wvalid 
); 

localparam X_SIZE = 640;
localparam Y_SIZE = 480; 
parameter REG_FILE_SIZE = 8;
localparam REG_FILE_AWIDTH = $clog2(REG_FILE_SIZE);
parameter AXI_LITE_ADDR_WIDTH = 8;

localparam AWAIT_WADD_AND_DATA = 3'b000;
localparam AWAIT_WDATA = 3'b001;
localparam AWAIT_WADD = 3'b010;
localparam AWAIT_WRITE = 3'b100;
localparam AWAIT_RESP = 3'b101;

localparam AWAIT_RADD = 2'b00;
localparam AWAIT_FETCH = 2'b01;
localparam AWAIT_READ = 2'b10;

localparam AXI_OK = 2'b00;
localparam AXI_ERR = 2'b10;

//initializing register file
reg [31:0]                          regfile [REG_FILE_SIZE-1:0];
reg [REG_FILE_AWIDTH-1:0]           writeAddr, readAddr;
reg [31:0]                          readData, writeData;
reg [1:0]                           readState = AWAIT_RADD;
reg [2:0]                           writeState = AWAIT_WADD_AND_DATA;

//Read from the register file 
always @(posedge s_axi_lite_aclk) begin

    readData <= regfile[readAddr];

    if(!axi_resetn) begin
        readState <= AWAIT_RADD;
    end 
    else case (readState)
        AWAIT_RADD: begin 
            if (s_axi_lite_arvalid) begin 
                readAddr <= s_axi_lite_araddr[2+:REG_FILE_AWIDTH]; //discard the bottom 2 bits because of byte addressing
                readState <= AWAIT_FETCH;
            end 
        end 

        AWAIT_FETCH: begin
            readState <= AWAIT_READ;
        end 

        AWAIT_READ: begin 
            if(s_axi_lite_rready) begin 
                readState <= AWAIT_RADD; 
            end 
        end 

        default: begin 
            readState <= AWAIT_RADD;
        end 
    endcase 
end 

assign s_axi_lite_arready = (readState == AWAIT_RADD); 
assign s_axi_lite_rresp = (readAddr < REG_FILE_SIZE) ? AXI_OK : AXI_ERR; 
assign s_axi_lite_rvalid = (readState == AWAIT_READ); 
assign s_axi_lite_rdata = readData; 

//Write to the register file, use a state machine to track address write, data write and response read events 
always @(posedge s_axi_lite_aclk) begin 
    if (!axi_resetn) begin
        writeState <= AWAIT_WADD_AND_DATA; 
    end 

    else case (writeState)
        AWAIT_WADD_AND_DATA: begin //IDLE, awaiting a write address or data - split into 3 different cases because both could arrive at different times
            case ({s_axi_lite_awvalid, s_axi_lite_wvalid}) 
                2'b10: begin //only address arrives
                    writeAddr <= s_axi_lite_awaddr[2+:REG_FILE_AWIDTH]; 
                    writeState <= AWAIT_WDATA;
                end 
                2'b01: begin //only data has arrived 
                    writeData <= s_axi_lite_wdata; 
                    writeState <= AWAIT_WADD; 
                end 
                2'b11: begin //both data and address has arrived
                    writeData <= s_axi_lite_wdata; 
                    writeAddr <= s_axi_lite_awaddr[2+:REG_FILE_AWIDTH]; 
                    writeState <= AWAIT_WRITE; 
                end 
                default: begin 
                    writeState <= AWAIT_WADD_AND_DATA; 
                end 
            endcase
        end 

        AWAIT_WDATA: begin //received address, waiting for data 
            if(s_axi_lite_wvalid) begin
                writeData <= s_axi_lite_wdata; 
                writeState <= AWAIT_WRITE; 
            end 
        end 

        AWAIT_WADD: begin //received data, waiting for address 
            if(s_axi_lite_awvalid) begin
                writeAddr <= s_axi_lite_awaddr[2+:REG_FILE_AWIDTH]; 
                writeState <= AWAIT_WRITE; 
            end
        end 

        AWAIT_WRITE: begin //Perform the write to the register file 
            regfile[writeAddr] <= writeData;
            writeState <= AWAIT_RESP;
        end 

        AWAIT_RESP: begin //wait to send response back to the CPU 
            if (s_axi_lite_bready) begin 
                writeState <= AWAIT_WADD_AND_DATA; 
            end 
        end 

        default: begin
            writeState <= AWAIT_WADD_AND_DATA; 
        end 
    endcase
end  

assign s_axi_lite_awready = (writeState == AWAIT_WADD_AND_DATA || writeState == AWAIT_WADD); 
assign s_axi_lite_wready = (writeState == AWAIT_WADD_AND_DATA || writeState == AWAIT_WDATA); 
assign s_axi_lite_bvalid = (writeState == AWAIT_RESP); 
assign s_axi_lite_bresp = (writeAddr < REG_FILE_SIZE) ? AXI_OK : AXI_ERR;

reg [9:0] x; 
reg [8:0] y; 

wire first = (x==0) & (y==0);
wire lastx = (x == X_SIZE-1);
wire lasty = (y == Y_SIZE-1); 

wire[7:0] frame = regfile[0]; 
wire ready; //backpressure from VDMA logic - is the VDMA ready to handle pixels? 

always @(posedge out_stream_aclk) begin 
    if (periph_resetn) begin
        if(ready && valid_int) begin //handshake procedure 
            if (lastx) begin 
                x <= 10'd0; 
                if(lasty) y <= 9'd0;
                else y <= y + 9'd1;
            end 
            else x <= x + 10'd1; 
        end
    end 
    else begin
        x <= 10'd0; 
        y <= 9'd0; 
    end 
end 

wire valid_int = 1'b1; //output is always valid since we are only converting pixel coordinates to colours

wire [7:0] r,g,b; 
assign r = x[7:0] + frame; 
assign g = y[7:0] + frame; 
assign b = x[6:0] + y[6:0] + frame; 

packer pixel_packer( 
    .aclk(out_stream_aclk), 
    .aresetn(periph_resetn), 
    .r(r), .g(g), .b(b), 
    .eol(lastx), 
    .in_stream_ready(ready), 
    .valid(valid_int), 
    .sof(first), 
    .out_stream_tdata(out_stream_tdata), 
    .out_stream_tkeep(out_stream_tkeep), 
    .out_stream_tlast(out_stream_tlast), 
    .out_stream_tready(out_stream_tready), 
    .out_stream_tvalid(out_stream_tvalid), 
    .out_stream_tuser(out_stream_tuser)
); 
endmodule

tb/test_AXIL.sv
`timescale 1ns / 1ps
module pixgen_tb; 

parameter REG_COUNT = 8; 

reg clk = 0;
reg rst = 0;
always #5 clk = !clk;

wire [31:0] dataOut;
wire [3:0] keep;
wire last, valid, user;

reg [7:0] writeAdd = 0;
reg [31:0] writeData = 0;
reg writeAddValid = 0, writeValid = 0;
wire writeAddReady, writeReady;

reg [7:0] readAdd = 0;
wire readAddReady;
reg readAddValid = 0;

wire [31:0] readData;
reg readReady = 0;
wire [1:0] readResp;
wire readValid;

reg respReady = 0;
wire [1:0] respData;
wire respValid;

pixel_generator p1 (
  .out_stream_aclk(clk),
  .s_axi_lite_aclk(clk),
  .axi_resetn(rst),
  .periph_resetn(rst),

//Stream output
  .out_stream_tdata(dataOut),
  .out_stream_tkeep(keep),
  .out_stream_tlast(last),
  .out_stream_tready(1'b1),
  .out_stream_tvalid(valid),
  .out_stream_tuser(user), 

//AXI-Lite S
  .s_axi_lite_araddr(readAdd),
  .s_axi_lite_arready(readAddReady),
  .s_axi_lite_arvalid(readAddValid),

  .s_axi_lite_awaddr(writeAdd),
  .s_axi_lite_awready(writeAddReady),
  .s_axi_lite_awvalid(writeAddValid),

  .s_axi_lite_bready(respReady),
  .s_axi_lite_bresp(respData),
  .s_axi_lite_bvalid(respValid),

  .s_axi_lite_rdata(readData),
  .s_axi_lite_rready(readReady),
  .s_axi_lite_rresp(readResp),
  .s_axi_lite_rvalid(readValid),

  .s_axi_lite_wdata(writeData),
  .s_axi_lite_wready(writeReady),
  .s_axi_lite_wvalid(writeValid));

integer i = 0; 
    initial begin 
        $dumpfile("test.vcd");
        $dumpvars(0, pixgen_tb);
        #16 rst = 1; 

        for(i = 0; i < REG_COUNT; i = i + 1) begin 
            #40 writeAdd = i*4; 
            writeData = i*32'h11111111; 
            #20 writeAddValid = 1; 
            #10 writeAddValid = 0; 
            #20 writeValid = 1; 
            #10 writeValid = 0; 
            #20 respReady = 1; 
            #10 respReady = 0; 
        end 

        for(i = 0; i < REG_COUNT; i = i + 1) begin 
            #40 readAdd = i*4; 
            #20 readAddValid = 1; 
            #10 readAddValid = 0; 
            #20 readReady = 1; 
            #10 readReady = 0; 
            $display(readData); 
        end 

        #100 $finish;
    end
endmodule

test.vcd
$date
	Mon Jun 08 17:55:06 2026
$end
$version
	Icarus Verilog
$end
$timescale
	1ps
$end
$scope module pixgen_tb $end
$var wire 4 ! keep [3:0] $end
$var wire 1 " writeReady $end
$var wire 1 # writeAddReady $end
$var wire 1 $ valid $end
$var wire 1 % user $end
$var wire 1 & respValid $end
$var wire 2 ' respData [1:0] $end
$var wire 1 ( readValid $end
$var wire 2 ) readResp [1:0] $end
$var wire 32 * readData [31:0] $end
$var wire 1 + readAddReady $end
$var wire 1 , last $end
$var wire 32 - dataOut [31:0] $end
$var parameter 32 . REG_COUNT $end
$var reg 1 / clk $end
$var reg 8 0 readAdd [7:0] $end
$var reg 1 1 readAddValid $end
$var reg 1 2 readReady $end
$var reg 1 3 respReady $end
$var reg 1 4 rst $end
$var reg 8 5 writeAdd [7:0] $end
$var reg 1 6 writeAddValid $end
$var reg 32 7 writeData [31:0] $end
$var reg 1 8 writeValid $end
$var integer 32 9 i [31:0] $end
$scope module p1 $end
$var wire 1 4 axi_resetn $end
$var wire 1 : first $end
$var wire 1 / out_stream_aclk $end
$var wire 4 ; out_stream_tkeep [3:0] $end
$var wire 1 < out_stream_tready $end
$var wire 1 4 periph_resetn $end
$var wire 1 / s_axi_lite_aclk $end
$var wire 8 = s_axi_lite_araddr [7:0] $end
$var wire 1 1 s_axi_lite_arvalid $end
$var wire 8 > s_axi_lite_awaddr [7:0] $end
$var wire 1 # s_axi_lite_awready $end
$var wire 1 6 s_axi_lite_awvalid $end
$var wire 1 3 s_axi_lite_bready $end
$var wire 32 ? s_axi_lite_rdata [31:0] $end
$var wire 1 2 s_axi_lite_rready $end
$var wire 32 @ s_axi_lite_wdata [31:0] $end
$var wire 1 " s_axi_lite_wready $end
$var wire 1 8 s_axi_lite_wvalid $end
$var wire 1 A valid_int $end
$var wire 1 ( s_axi_lite_rvalid $end
$var wire 2 B s_axi_lite_rresp [1:0] $end
$var wire 1 & s_axi_lite_bvalid $end
$var wire 2 C s_axi_lite_bresp [1:0] $end
$var wire 1 + s_axi_lite_arready $end
$var wire 1 D ready $end
$var wire 8 E r [7:0] $end
$var wire 1 $ out_stream_tvalid $end
$var wire 1 % out_stream_tuser $end
$var wire 1 , out_stream_tlast $end
$var wire 32 F out_stream_tdata [31:0] $end
$var wire 1 G lasty $end
$var wire 1 H lastx $end
$var wire 8 I g [7:0] $end
$var wire 8 J frame [7:0] $end
$var wire 8 K b [7:0] $end
$var parameter 2 L AWAIT_FETCH $end
$var parameter 2 M AWAIT_RADD $end
$var parameter 2 N AWAIT_READ $end
$var parameter 3 O AWAIT_RESP $end
$var parameter 3 P AWAIT_WADD $end
$var parameter 3 Q AWAIT_WADD_AND_DATA $end
$var parameter 3 R AWAIT_WDATA $end
$var parameter 3 S AWAIT_WRITE $end
$var parameter 2 T AXI_ERR $end
$var parameter 32 U AXI_LITE_ADDR_WIDTH $end
$var parameter 2 V AXI_OK $end
$var parameter 32 W REG_FILE_AWIDTH $end
$var parameter 32 X REG_FILE_SIZE $end
$var parameter 32 Y X_SIZE $end
$var parameter 32 Z Y_SIZE $end
$var reg 3 [ readAddr [2:0] $end
$var reg 32 \ readData [31:0] $end
$var reg 2 ] readState [1:0] $end
$var reg 3 ^ writeAddr [2:0] $end
$var reg 32 _ writeData [31:0] $end
$var reg 3 ` writeState [2:0] $end
$var reg 10 a x [9:0] $end
$var reg 9 b y [8:0] $end
$scope module pixel_packer $end
$var wire 1 / aclk $end
$var wire 1 4 aresetn $end
$var wire 8 c b [7:0] $end
$var wire 1 H eol $end
$var wire 8 d g [7:0] $end
$var wire 1 D in_stream_ready $end
$var wire 32 e out_stream_tdata [31:0] $end
$var wire 4 f out_stream_tkeep [3:0] $end
$var wire 1 , out_stream_tlast $end
$var wire 1 < out_stream_tready $end
$var wire 1 % out_stream_tuser $end
$var wire 1 $ out_stream_tvalid $end
$var wire 8 g r [7:0] $end
$var wire 1 : sof $end
$var wire 1 A valid $end
$var wire 1 h state0 $end
$var wire 2 i state [1:0] $end
$var reg 8 j last_b [7:0] $end
$var reg 8 k last_g [7:0] $end
$var reg 8 l last_r [7:0] $end
$var reg 1 m ready $end
$var reg 1 n sof_reg $end
$var reg 2 o state_reg [1:0] $end
$var reg 32 p tdata [31:0] $end
$var reg 1 q tvalid $end
$upscope $end
$upscope $end
$upscope $end
$enddefinitions $end
$comment Show the parameter values. $end
$dumpall
b111100000 Z
b1010000000 Y
b1000 X
b11 W
b0 V
b1000 U
b10 T
b100 S
b1 R
b0 Q
b10 P
b101 O
b10 N
b0 M
b1 L
b1000 .
$end
#0
$dumpvars
0q
bx p
b0 o
xn
1m
bx l
bx k
bx j
b0 i
1h
bx g
b1111 f
bx e
bx d
bx c
bx b
bx a
b0 `
bx _
bx ^
b0 ]
bx \
bx [
bx K
bx J
bx I
xH
xG
bx F
bx E
1D
bx0 C
bx0 B
1A
b0 @
bx ?
b0 >
b0 =
1<
b1111 ;
x:
b0 9
08
b0 7
06
b0 5
04
03
02
01
b0 0
0/
bx -
x,
1+
bx *
bx0 )
0(
bx0 '
0&
x%
0$
1#
1"
b1111 !
$end
#5000
1:
0%
0n
0G
b0 b
0,
0H
b0 a
1/
#10000
0/
#15000
1/
#16000
14
#20000
0/
#25000
1$
1q
0h
b1 i
0:
1%
1n
b1 o
b1 a
1/
#30000
0/
#35000
b10 i
b10 a
0%
0n
b10 o
1/
#40000
0/
#45000
b11 i
b11 o
b11 a
1/
#50000
0/
#55000
0$
0q
1h
b0 i
b100 a
b0 o
1/
#60000
0/
#65000
1$
1q
0h
b1 i
b1 o
b101 a
1/
#70000
0/
#75000
b10 i
b110 a
b10 o
1/
#76000
16
#80000
0/
#85000
b11 i
0#
b0 '
b0 C
b11 o
b1 `
b0 ^
b111 a
1/
#86000
06
#90000
0/
#95000
0$
0q
1h
b0 i
b1000 a
b0 o
1/
#100000
0/
#105000
1$
1q
0h
b1 i
b1 o
b1001 a
1/
#106000
18
#110000
0/
#115000
0"
b10 i
b1010 a
b100 `
b0 _
b10 o
1/
#116000
08
#120000
0/
#125000
b10110000101100000000xxxxxxxx -
b10110000101100000000xxxxxxxx F
b10110000101100000000xxxxxxxx e
b10110000101100000000xxxxxxxx p
b11 i
b1011 E
b1011 g
b0 I
b0 d
b1011 K
b1011 c
b0 J
b11 o
1&
b101 `
b1011 a
1/
#130000
0/
#135000
b1100 E
b1100 g
b1100 K
b1100 c
0$
0q
b10110000101100000000 -
b10110000101100000000 F
b10110000101100000000 e
b10110000101100000000 p
1h
b0 i
b1100 a
b1011 j
b0 k
b1011 l
b0 o
1/
#136000
13
#140000
0/
#145000
1$
1q
b11000000110000000000 -
b11000000110000000000 F
b11000000110000000000 e
b11000000110000000000 p
0h
b1 i
1#
1"
b1101 E
b1101 g
b1101 K
b1101 c
b1100 j
b1100 l
b1 o
0&
b0 `
b1101 a
1/
#146000
b1 9
03
#150000
0/
#155000
b1110 E
b1110 g
b1110 K
b1110 c
b1110000000000000110100001101 -
b1110000000000000110100001101 F
b1110000000000000110100001101 e
b1110000000000000110100001101 p
b10 i
b1110 a
b1101 j
b1101 l
b10 o
1/
#160000
0/
#165000
b1111000011110000000000001110 -
b1111000011110000000000001110 F
b1111000011110000000000001110 e
b1111000011110000000000001110 p
b11 i
b1111 E
b1111 g
b1111 K
b1111 c
b1110 j
b1110 l
b11 o
b1111 a
1/
#170000
0/
#175000
b10000 E
b10000 g
b10000 K
b10000 c
0$
0q
b11110000111100000000 -
b11110000111100000000 F
b11110000111100000000 e
b11110000111100000000 p
1h
b0 i
b10000 a
b1111 j
b1111 l
b0 o
1/
#180000
0/
#185000
1$
1q
b100000001000000000000 -
b100000001000000000000 F
b100000001000000000000 e
b100000001000000000000 p
0h
b1 i
b10001 E
b10001 g
b10001 K
b10001 c
b10000 j
b10000 l
b1 o
b10001 a
1/
#186000
b10001000100010001000100010001 7
b10001000100010001000100010001 @
b100 5
b100 >
#190000
0/
#195000
b10010 E
b10010 g
b10010 K
b10010 c
b10010000000000001000100010001 -
b10010000000000001000100010001 F
b10010000000000001000100010001 e
b10010000000000001000100010001 p
b10 i
b10010 a
b10001 j
b10001 l
b10 o
1/
#200000
0/
#205000
b10011000100110000000000010010 -
b10011000100110000000000010010 F
b10011000100110000000000010010 e
b10011000100110000000000010010 p
b11 i
b10011 E
b10011 g
b10011 K
b10011 c
b10010 j
b10010 l
b11 o
b10011 a
1/
#206000
16
#210000
0/
#215000
b10100 E
b10100 g
b10100 K
b10100 c
0#
0$
0q
b100110001001100000000 -
b100110001001100000000 F
b100110001001100000000 e
b100110001001100000000 p
1h
b0 i
b10100 a
b1 `
b1 ^
b10011 j
b10011 l
b0 o
1/
#216000
06
#220000
0/
#225000
1$
1q
b101000001010000000000 -
b101000001010000000000 F
b101000001010000000000 e
b101000001010000000000 p
0h
b1 i
b10101 E
b10101 g
b10101 K
b10101 c
b10100 j
b10100 l
b1 o
b10101 a
1/
#230000
0/
#235000
b10110 E
b10110 g
b10110 K
b10110 c
b10110000000000001010100010101 -
b10110000000000001010100010101 F
b10110000000000001010100010101 e
b10110000000000001010100010101 p
b10 i
b10110 a
b10101 j
b10101 l
b10 o
1/
#236000
18
#240000
0/
#245000
b10111000101110000000000010110 -
b10111000101110000000000010110 F
b10111000101110000000000010110 e
b10111000101110000000000010110 p
b11 i
0"
b10111 E
b10111 g
b10111 K
b10111 c
b10110 j
b10110 l
b11 o
b100 `
b10001000100010001000100010001 _
b10111 a
1/
#246000
08
#250000
0/
#255000
b11000 E
b11000 g
b11000 K
b11000 c
0$
0q
b101110001011100000000 -
b101110001011100000000 F
b101110001011100000000 e
b101110001011100000000 p
1h
b0 i
b11000 a
1&
b101 `
b10111 j
b10111 l
b0 o
1/
#260000
0/
#265000
1$
1q
b110000001100000000000 -
b110000001100000000000 F
b110000001100000000000 e
b110000001100000000000 p
0h
b1 i
b11001 E
b11001 g
b11001 K
b11001 c
b11000 j
b11000 l
b1 o
b11001 a
1/
#266000
13
#270000
0/
#275000
b11010 E
b11010 g
b11010 K
b11010 c
1#
1"
b11010000000000001100100011001 -
b11010000000000001100100011001 F
b11010000000000001100100011001 e
b11010000000000001100100011001 p
b10 i
b11010 a
0&
b0 `
b11001 j
b11001 l
b10 o
1/
#276000
b10 9
03
#280000
0/
#285000
b11011000110110000000000011010 -
b11011000110110000000000011010 F
b11011000110110000000000011010 e
b11011000110110000000000011010 p
b11 i
b11011 E
b11011 g
b11011 K
b11011 c
b11010 j
b11010 l
b11 o
b11011 a
1/
#290000
0/
#295000
b11100 E
b11100 g
b11100 K
b11100 c
0$
0q
b110110001101100000000 -
b110110001101100000000 F
b110110001101100000000 e
b110110001101100000000 p
1h
b0 i
b11100 a
b11011 j
b11011 l
b0 o
1/
#300000
0/
#305000
1$
1q
b111000001110000000000 -
b111000001110000000000 F
b111000001110000000000 e
b111000001110000000000 p
0h
b1 i
b11101 E
b11101 g
b11101 K
b11101 c
b11100 j
b11100 l
b1 o
b11101 a
1/
#310000
0/
#315000
b11110 E
b11110 g
b11110 K
b11110 c
b11110000000000001110100011101 -
b11110000000000001110100011101 F
b11110000000000001110100011101 e
b11110000000000001110100011101 p
b10 i
b11110 a
b11101 j
b11101 l
b10 o
1/
#316000
b100010001000100010001000100010 7
b100010001000100010001000100010 @
b1000 5
b1000 >
#320000
0/
#325000
b11111000111110000000000011110 -
b11111000111110000000000011110 F
b11111000111110000000000011110 e
b11111000111110000000000011110 p
b11 i
b11111 E
b11111 g
b11111 K
b11111 c
b11110 j
b11110 l
b11 o
b11111 a
1/
#330000
0/
#335000
b100000 E
b100000 g
b100000 K
b100000 c
0$
0q
b111110001111100000000 -
b111110001111100000000 F
b111110001111100000000 e
b111110001111100000000 p
1h
b0 i
b100000 a
b11111 j
b11111 l
b0 o
1/
#336000
16
#340000
0/
#345000
1$
1q
b1000000010000000000000 -
b1000000010000000000000 F
b1000000010000000000000 e
b1000000010000000000000 p
0h
b1 i
0#
b100001 E
b100001 g
b100001 K
b100001 c
b100000 j
b100000 l
b1 o
b1 `
b10 ^
b100001 a
1/
#346000
06
#350000
0/
#355000
b100010 E
b100010 g
b100010 K
b100010 c
b100010000000000010000100100001 -
b100010000000000010000100100001 F
b100010000000000010000100100001 e
b100010000000000010000100100001 p
b10 i
b100010 a
b100001 j
b100001 l
b10 o
1/
#360000
0/
#365000
b100011001000110000000000100010 -
b100011001000110000000000100010 F
b100011001000110000000000100010 e
b100011001000110000000000100010 p
b11 i
b100011 E
b100011 g
b100011 K
b100011 c
b100010 j
b100010 l
b11 o
b100011 a
1/
#366000
18
#370000
0/
#375000
b100100 E
b100100 g
b100100 K
b100100 c
0"
0$
0q
b1000110010001100000000 -
b1000110010001100000000 F
b1000110010001100000000 e
b1000110010001100000000 p
1h
b0 i
b100100 a
b100 `
b100010001000100010001000100010 _
b100011 j
b100011 l
b0 o
1/
#376000
08
#380000
0/
#385000
1$
1q
b1001000010010000000000 -
b1001000010010000000000 F
b1001000010010000000000 e
b1001000010010000000000 p
0h
b1 i
b100101 E
b100101 g
b100101 K
b100101 c
b100100 j
b100100 l
b1 o
1&
b101 `
b100101 a
1/
#390000
0/
#395000
b100110 E
b100110 g
b100110 K
b100110 c
b100110000000000010010100100101 -
b100110000000000010010100100101 F
b100110000000000010010100100101 e
b100110000000000010010100100101 p
b10 i
b100110 a
b100101 j
b100101 l
b10 o
1/
#396000
13
#400000
0/
#405000
b100111001001110000000000100110 -
b100111001001110000000000100110 F
b100111001001110000000000100110 e
b100111001001110000000000100110 p
b11 i
1#
1"
b100111 E
b100111 g
b100111 K
b100111 c
b100110 j
b100110 l
b11 o
0&
b0 `
b100111 a
1/
#406000
b11 9
03
#410000
0/
#415000
b101000 E
b101000 g
b101000 K
b101000 c
0$
0q
b1001110010011100000000 -
b1001110010011100000000 F
b1001110010011100000000 e
b1001110010011100000000 p
1h
b0 i
b101000 a
b100111 j
b100111 l
b0 o
1/
#420000
0/
#425000
1$
1q
b1010000010100000000000 -
b1010000010100000000000 F
b1010000010100000000000 e
b1010000010100000000000 p
0h
b1 i
b101001 E
b101001 g
b101001 K
b101001 c
b101000 j
b101000 l
b1 o
b101001 a
1/
#430000
0/
#435000
b101010 E
b101010 g
b101010 K
b101010 c
b101010000000000010100100101001 -
b101010000000000010100100101001 F
b101010000000000010100100101001 e
b101010000000000010100100101001 p
b10 i
b101010 a
b101001 j
b101001 l
b10 o
1/
#440000
0/
#445000
b101011001010110000000000101010 -
b101011001010110000000000101010 F
b101011001010110000000000101010 e
b101011001010110000000000101010 p
b11 i
b101011 E
b101011 g
b101011 K
b101011 c
b101010 j
b101010 l
b11 o
b101011 a
1/
#446000
b110011001100110011001100110011 7
b110011001100110011001100110011 @
b1100 5
b1100 >
#450000
0/
#455000
b101100 E
b101100 g
b101100 K
b101100 c
0$
0q
b1010110010101100000000 -
b1010110010101100000000 F
b1010110010101100000000 e
b1010110010101100000000 p
1h
b0 i
b101100 a
b101011 j
b101011 l
b0 o
1/
#460000
0/
#465000
1$
1q
b1011000010110000000000 -
b1011000010110000000000 F
b1011000010110000000000 e
b1011000010110000000000 p
0h
b1 i
b101101 E
b101101 g
b101101 K
b101101 c
b101100 j
b101100 l
b1 o
b101101 a
1/
#466000
16
#470000
0/
#475000
b101110 E
b101110 g
b101110 K
b101110 c
0#
b101110000000000010110100101101 -
b101110000000000010110100101101 F
b101110000000000010110100101101 e
b101110000000000010110100101101 p
b10 i
b101110 a
b1 `
b11 ^
b101101 j
b101101 l
b10 o
1/
#476000
06
#480000
0/
#485000
b101111001011110000000000101110 -
b101111001011110000000000101110 F
b101111001011110000000000101110 e
b101111001011110000000000101110 p
b11 i
b101111 E
b101111 g
b101111 K
b101111 c
b101110 j
b101110 l
b11 o
b101111 a
1/
#490000
0/
#495000
b110000 E
b110000 g
b110000 K
b110000 c
0$
0q
b1011110010111100000000 -
b1011110010111100000000 F
b1011110010111100000000 e
b1011110010111100000000 p
1h
b0 i
b110000 a
b101111 j
b101111 l
b0 o
1/
#496000
18
#500000
0/
#505000
1$
1q
b1100000011000000000000 -
b1100000011000000000000 F
b1100000011000000000000 e
b1100000011000000000000 p
0h
b1 i
0"
b110001 E
b110001 g
b110001 K
b110001 c
b110000 j
b110000 l
b1 o
b100 `
b110011001100110011001100110011 _
b110001 a
1/
#506000
08
#510000
0/
#515000
b110010 E
b110010 g
b110010 K
b110010 c
b110010000000000011000100110001 -
b110010000000000011000100110001 F
b110010000000000011000100110001 e
b110010000000000011000100110001 p
b10 i
b110010 a
1&
b101 `
b110001 j
b110001 l
b10 o
1/
#520000
0/
#525000
b110011001100110000000000110010 -
b110011001100110000000000110010 F
b110011001100110000000000110010 e
b110011001100110000000000110010 p
b11 i
b110011 E
b110011 g
b110011 K
b110011 c
b110010 j
b110010 l
b11 o
b110011 a
1/
#526000
13
#530000
0/
#535000
b110100 E
b110100 g
b110100 K
b110100 c
1#
1"
0$
0q
b1100110011001100000000 -
b1100110011001100000000 F
b1100110011001100000000 e
b1100110011001100000000 p
1h
b0 i
b110100 a
0&
b0 `
b110011 j
b110011 l
b0 o
1/
#536000
b100 9
03
#540000
0/
#545000
1$
1q
b1101000011010000000000 -
b1101000011010000000000 F
b1101000011010000000000 e
b1101000011010000000000 p
0h
b1 i
b110101 E
b110101 g
b110101 K
b110101 c
b110100 j
b110100 l
b1 o
b110101 a
1/
#550000
0/
#555000
b110110 E
b110110 g
b110110 K
b110110 c
b110110000000000011010100110101 -
b110110000000000011010100110101 F
b110110000000000011010100110101 e
b110110000000000011010100110101 p
b10 i
b110110 a
b110101 j
b110101 l
b10 o
1/
#560000
0/
#565000
b110111001101110000000000110110 -
b110111001101110000000000110110 F
b110111001101110000000000110110 e
b110111001101110000000000110110 p
b11 i
b110111 E
b110111 g
b110111 K
b110111 c
b110110 j
b110110 l
b11 o
b110111 a
1/
#570000
0/
#575000
b111000 E
b111000 g
b111000 K
b111000 c
0$
0q
b1101110011011100000000 -
b1101110011011100000000 F
b1101110011011100000000 e
b1101110011011100000000 p
1h
b0 i
b111000 a
b110111 j
b110111 l
b0 o
1/
#576000
b1000100010001000100010001000100 7
b1000100010001000100010001000100 @
b10000 5
b10000 >
#580000
0/
#585000
1$
1q
b1110000011100000000000 -
b1110000011100000000000 F
b1110000011100000000000 e
b1110000011100000000000 p
0h
b1 i
b111001 E
b111001 g
b111001 K
b111001 c
b111000 j
b111000 l
b1 o
b111001 a
1/
#590000
0/
#595000
b111010 E
b111010 g
b111010 K
b111010 c
b111010000000000011100100111001 -
b111010000000000011100100111001 F
b111010000000000011100100111001 e
b111010000000000011100100111001 p
b10 i
b111010 a
b111001 j
b111001 l
b10 o
1/
#596000
16
#600000
0/
