HDL/input_builder.sv
module input_builder #(
    parameter int N_FEATURES = 16
)(
    input  logic        clk,
    input  logic        resetn,
    input  logic [9:0]  pixel_x,
    input  logic [8:0]  pixel_y,
    input  logic [5:0]  axis_x_select,
    input  logic [5:0]  axis_y_select,
    input  logic signed [15:0] feature_regs [N_FEATURES-1:0],
    output logic signed [15:0] x            [N_FEATURES-1:0]
);

    // 1/639 in Q1.15: round(32768/639) = 51
    // 1/479 in Q1.15: round(32768/479) = 68
    localparam logic [15:0] INV_639 = 16'd51;
    localparam logic [15:0] INV_479 = 16'd68;

    logic [25:0] x_norm_full;
    logic [25:0] y_norm_full;
    logic signed [15:0] x_norm;
    logic signed [15:0] y_norm;

    always_comb begin
        x_norm_full = pixel_x * INV_639;
        y_norm_full = pixel_y * INV_479;
        x_norm      = x_norm_full[15:0];
        y_norm      = y_norm_full[15:0];
    end

    always_ff @(posedge clk) begin
        if (!resetn) begin
            for (int i = 0; i < N_FEATURES; i++)
                x[i] <= '0;
        end else begin
            for (int i = 0; i < N_FEATURES; i++) begin
                if (i == axis_x_select)
                    x[i] <= x_norm;
                else if (i == axis_y_select)
                    x[i] <= y_norm;
                else
                    x[i] <= feature_regs[i];
            end
        end
    end

endmodule

Learning/hdl/tb_input_builder.v
`timescale 1ns / 1ps
module tb_input_builder;

    localparam N_FEATURES = 4;

    reg         clk    = 0;
    reg         resetn = 0;
    reg [9:0]   pixel_x = 0;
    reg [8:0]   pixel_y = 0;
    reg [5:0]   axis_x_select = 0;
    reg [5:0]   axis_y_select = 1;

    reg signed [15:0] feature_regs [N_FEATURES-1:0];
    wire signed [15:0] x [N_FEATURES-1:0];

    always #5 clk = !clk;

    input_builder #(
        .N_FEATURES(N_FEATURES)
    ) uut (
        .clk(clk),
        .resetn(resetn),
        .pixel_x(pixel_x),
        .pixel_y(pixel_y),
        .axis_x_select(axis_x_select),
        .axis_y_select(axis_y_select),
        .feature_regs(feature_regs),
        .x(x)
    );

    initial begin
        $dumpfile("tb_input.vcd");
        $dumpvars(0, tb_input_builder);

        // set feature registers
        feature_regs[0] = 16'sd8192;  // 0.25
        feature_regs[1] = 16'sd16384; // 0.5
        feature_regs[2] = 16'sd24576; // 0.75
        feature_regs[3] = 16'sd32767; // ~1.0

        #20 resetn = 1;

        // TEST 1 - middle of screen
        // axis_x=0, axis_y=1
        // x[0] should be pixel_x/639 = 320/639 ≈ 0.5
        // x[1] should be pixel_y/479 = 240/479 ≈ 0.5
        // x[2] should be feature_regs[2] = 0.75
        // x[3] should be feature_regs[3] = ~1.0
        pixel_x = 320;
        pixel_y = 240;
        @(posedge clk);
        @(posedge clk); // one cycle latency
        #1;
        $display("TEST 1 - middle of screen");
        $display("x[0] = %0d expected ~16320 (0.498) -- %s", x[0], (x[0] > 16000 && x[0] < 16500) ? "PASS" : "FAIL");
        $display("x[1] = %0d expected ~16320 (0.498) -- %s", x[1], (x[1] > 16000 && x[1] < 16500) ? "PASS" : "FAIL");
        $display("x[2] = %0d expected 24576 (0.75)  -- %s", x[2], x[2] == 24576 ? "PASS" : "FAIL");
        $display("x[3] = %0d expected 32767 (~1.0)  -- %s", x[3], x[3] == 32767 ? "PASS" : "FAIL");

        // TEST 2 - top left corner
        // x[0] should be 0, x[1] should be 0
        pixel_x = 0;
        pixel_y = 0;
        @(posedge clk);
        @(posedge clk);
        #1;
        $display("TEST 2 - top left corner");
        $display("x[0] = %0d expected 0 -- %s", x[0], x[0] == 0 ? "PASS" : "FAIL");
        $display("x[1] = %0d expected 0 -- %s", x[1], x[1] == 0 ? "PASS" : "FAIL");

        // TEST 3 - bottom right corner
        // x[0] should be ~32767, x[1] should be ~32767
        pixel_x = 639;
        pixel_y = 479;
        @(posedge clk);
        @(posedge clk);
        #1;
        $display("TEST 3 - bottom right corner");
        $display("x[0] = %0d expected ~32589 (~1.0) -- %s", x[0], (x[0] > 32000) ? "PASS" : "FAIL");
        $display("x[1] = %0d expected ~32572 (~1.0) -- %s", x[1], (x[1] > 32000) ? "PASS" : "FAIL");

        #20 $finish;
    end

endmodule

Learning/hdl/tb_input.vcd
$date
	Tue May 26 15:17:37 2026
$end
$version
	Icarus Verilog
$end
$timescale
	1ps
$end
$scope module tb_input_builder $end
$var parameter 32 ! N_FEATURES $end
$var reg 6 " axis_x_select [5:0] $end
$var reg 6 # axis_y_select [5:0] $end
$var reg 1 $ clk $end
$var reg 10 % pixel_x [9:0] $end
$var reg 9 & pixel_y [8:0] $end
$var reg 1 ' resetn $end
$scope module uut $end
$var wire 6 ( axis_x_select [5:0] $end
$var wire 6 ) axis_y_select [5:0] $end
$var wire 1 $ clk $end
$var wire 10 * pixel_x [9:0] $end
$var wire 9 + pixel_y [8:0] $end
$var wire 1 ' resetn $end
$var wire 26 , y_norm_full [25:0] $end
$var wire 16 - y_norm [15:0] $end
$var wire 26 . x_norm_full [25:0] $end
$var wire 16 / x_norm [15:0] $end
$var parameter 16 0 INV_479 $end
$var parameter 16 1 INV_639 $end
$var parameter 32 2 N_FEATURES $end
$var integer 32 3 i [31:0] $end
$upscope $end
$upscope $end
$enddefinitions $end
$comment Show the parameter values. $end
$dumpall
b100 2
b110011 1
b1000100 0
b100 !
$end
#0
$dumpvars
bx 3
b0 /
b0 .
b0 -
b0 ,
b0 +
b0 *
b1 )
b0 (
0'
b0 &
b0 %
0$
b1 #
b0 "
$end
#5000
b100 3
1$
#10000
0$
#15000
b100 3
1$
#20000
b11111111000000 -
b11111111000000 /
b11111111000000 ,
b11111111000000 .
0$
b11110000 &
b11110000 +
b101000000 %
b101000000 *
1'
#25000
b100 3
1$
#30000
0$
#35000
b100 3
1$
#36000
b0 -
b0 /
b0 ,
b0 .
b0 &
b0 +
b0 %
b0 *
#40000
0$
#45000
b100 3
1$
#50000
0$
#55000
b100 3
1$
#56000
b111111100111100 -
b111111101001101 /
b111111100111100 ,
b111111101001101 .
b111011111 &
b111011111 +
b1001111111 %
b1001111111 *
#60000
0$
#65000
b100 3
1$
#70000
0$
#75000
b100 3
1$
#80000
0$
#85000
b100 3
1$
#90000
0$
#95000
b100 3
1$
